pipmanager/__init__.py
pipmanager/main.py
pipmanagergui-0.2.0.dist-info/LICENSE
pipmanagergui-0.2.0.dist-info/METADATA
pipmanagergui-0.2.0.dist-info/WHEEL
pipmanagergui-0.2.0.dist-info/entry_points.txt
pipmanagergui-0.2.0.dist-info/top_level.txt
pipmanagergui-0.2.0.dist-info/RECORD
