Metadata-Version: 2.2
Name: pipmanagergui
Version: 0.2.0
Summary: A GUI for managing Python packages
Home-page: https://github.com/teymuur/pipmanagergui
Author: Teymur Babayev
Author-email: teymur_babayev08@yahoo.com
License: MIT
Classifier: Programming Language :: Python :: 3
Classifier: License :: OSI Approved :: MIT License
Classifier: Operating System :: OS Independent
Requires-Python: >=3.8
License-File: LICENSE
Requires-Dist: requests
Dynamic: author
Dynamic: author-email
Dynamic: classifier
Dynamic: description
Dynamic: description-content-type
Dynamic: home-page
Dynamic: license
Dynamic: requires-dist
Dynamic: requires-python
Dynamic: summary
